dymo_cli/__init__.py
dymo_cli/api.py
dymo_cli/cli.py
dymo_cli/config.py
dymo_cli/detection.py
dymo_cli/ui.py
dymo_cli/utils.py
dymo_cli-0.1.1.dist-info/licenses/LICENSE
dymo_cli-0.1.1.dist-info/METADATA
dymo_cli-0.1.1.dist-info/WHEEL
dymo_cli-0.1.1.dist-info/entry_points.txt
dymo_cli-0.1.1.dist-info/top_level.txt
dymo_cli-0.1.1.dist-info/RECORD
