Metadata-Version: 2.4
Name: dymo-cli
Version: 0.1.1
License-File: LICENSE
Requires-Dist: rich
Requires-Dist: prompt_toolkit
Requires-Dist: requests
Requires-Dist: dymoapi
Dynamic: license-file
Dynamic: requires-dist
